example_package_kian/__init__.py
example_package_kian/example.py
example_package_kian-0.0.3.dist-info/METADATA
example_package_kian-0.0.3.dist-info/WHEEL
example_package_kian-0.0.3.dist-info/licenses/LICENSE
example_package_kian-0.0.3.dist-info/RECORD
