Metadata-Version: 2.1
Name: example_package_kian
Version: 0.0.3
Summary: A small example package
Project-URL: Homepage, https://github.com/pypa/sampleproject
Project-URL: Bug Tracker, https://github.com/pypa/sampleproject/issues
Author-email: kian kyars <kiankyars@gmail.com>
Maintainer-email: andrej karpathy <andrej.karpathy@gmail.com>, leo gao <leogao31@gmail.com>
License-File: LICENSE
Classifier: License :: OSI Approved :: MIT License
Classifier: Operating System :: OS Independent
Classifier: Programming Language :: Python :: 3
Requires-Python: >=3.11
